dashai_plugin_prueba_alanezz/__init__.py
dashai_plugin_prueba_alanezz/mlp_image_classifier.py
dashai_plugin_prueba_alanezz-0.0.1.dist-info/METADATA
dashai_plugin_prueba_alanezz-0.0.1.dist-info/WHEEL
dashai_plugin_prueba_alanezz-0.0.1.dist-info/entry_points.txt
dashai_plugin_prueba_alanezz-0.0.1.dist-info/RECORD
